conf.py
pypi_sphinx_flexlate_example/__init__.py
version.py
pypi_sphinx_flexlate_example-0.86.0.dist-info/WHEEL
pypi_sphinx_flexlate_example-0.86.0.dist-info/LICENSE.md
pypi_sphinx_flexlate_example-0.86.0.dist-info/METADATA
pypi_sphinx_flexlate_example-0.86.0.dist-info/RECORD
