Metadata-Version: 2.1
Name: pypi-sphinx-flexlate-example
Version: 0.86.0
Summary: Example output for https://github.com/nickderobertis/copier-pypi-sphinx-flexlate
License: MIT
Author: Nick DeRobertis
Author-email: derobertis.nick@gmail.com
Requires-Python: >=3.8
Classifier: Development Status :: 3 - Alpha
Classifier: Intended Audience :: Developers
Classifier: License :: OSI Approved :: MIT License
Classifier: Programming Language :: Python :: 3
Classifier: Programming Language :: Python :: 3.8
Classifier: Programming Language :: Python :: 3.9
Classifier: Programming Language :: Python :: 3.10
Classifier: Programming Language :: Python :: 3.11
Classifier: Programming Language :: Python :: 3.10
Classifier: Programming Language :: Python :: 3.11
Classifier: Programming Language :: Python :: 3.7
Classifier: Programming Language :: Python :: 3.8
Classifier: Programming Language :: Python :: 3.9
Project-URL: documentation, https://nickderobertis.github.io/pypi-sphinx-flexlate-example
Project-URL: repository, https://github.com/nickderobertis/pypi-sphinx-flexlate-example
